type_intersections/__init__.py
type_intersections-0.1.1.dist-info/LICENSE
type_intersections-0.1.1.dist-info/WHEEL
type_intersections-0.1.1.dist-info/METADATA
type_intersections-0.1.1.dist-info/RECORD
