Metadata-Version: 2.1
Name: type-intersections
Version: 0.1.1
Summary: 
Home-page: https://github.com/ovsyanka83/type-intersections
License: MIT
Author: Stanislav Zmiev
Author-email: szmiev2000@gmail.com
Requires-Python: >=3.11,<4.0
Classifier: License :: OSI Approved :: MIT License
Classifier: Programming Language :: Python :: 3
Classifier: Programming Language :: Python :: 3.11
Project-URL: Repository, https://github.com/ovsyanka83/type-intersections
